drawn/__init__.py
drawn-0.0.1.dist-info/METADATA
drawn-0.0.1.dist-info/WHEEL
drawn-0.0.1.dist-info/RECORD
